MANIFEST.in
requirements.txt
setup.py
xossh
xosapi/VERSION
xosapi/__init__.py
xosapi/orm.py
xosapi/version.py
xosapi/xos_grpc_client.py
xosapi.egg-info/PKG-INFO
xosapi.egg-info/SOURCES.txt
xosapi.egg-info/dependency_links.txt
xosapi.egg-info/requires.txt
xosapi.egg-info/top_level.txt
xosapi/chameleon_client/__init__.py
xosapi/chameleon_client/asleep.py
xosapi/chameleon_client/grpc_client.py
xosapi/chameleon_client/protoc_plugins/gw_gen.py
xosapi/chameleon_client/protos/__init__.py
xosapi/chameleon_client/protos/schema_pb2.py
xosapi/chameleon_client/protos/schema_pb2_grpc.py
xosapi/chameleon_client/protos/google/api/annotations.proto
xosapi/chameleon_client/protos/google/api/http.proto
xosapi/convenience/__init__.py
xosapi/convenience/addresspool.py
xosapi/convenience/controller.py
xosapi/convenience/instance.py
xosapi/convenience/network.py
xosapi/convenience/onosapp.py
xosapi/convenience/port.py
xosapi/convenience/privilege.py
xosapi/convenience/service.py
xosapi/convenience/serviceinstance.py
xosapi/convenience/slice.py
xosapi/convenience/tag.py
xosapi/convenience/user.py