Metadata-Version: 1.1
Name: xosapi
Version: 4.0.2
Summary: XOS API client
Home-page: UNKNOWN
Author: UNKNOWN
Author-email: UNKNOWN
License: Apache v2
Platform: UNKNOWN
Classifier: License :: OSI Approved :: Apache Software License
